{
    "SecureInfrastructure" : {
      "overview" : "Secure Infrastructure refers to the establishment of robust and resilient systems that safeguard digital assets and data against unauthorized access, breaches, and cyber threats. It involves implementing a combination of hardware, software, policies, and procedures designed to protect networks, servers, applications, and other critical components from vulnerabilities and attacks. By prioritizing security measures such as encryption, access controls, and regular audits, organizations can mitigate risks and ensure the integrity and confidentiality of their infrastructure.",
      "qnum" : "1",
      "title" : "Secure Infrastructure",
      "1": "Config Management",
      "1-summary": "Configuration management is the systematic process of managing and controlling changes to a systems configuration ensuring consistantly, reliability and traceability throughout its lifecycle",
      "1-tier": "Foundation",
      "1-points": "1",
      "2": "Segmentation / Isolation",
      "2-summary": "",
      "2-tier": "Foundation",
      "2-points": "2",
      "3": "Logging & Monitoring",
      "3-summary": "",
      "3-tier": "Strategic",
      "3-points": "3",
      "4": "Automated Policy / Enforcement",
      "4-summary": "",
      "4-tier": "Strategic",
      "4-points": "4",
      "5": "Secrets Management",
      "5-summary": "",
      "5-tier": "Strategic",
      "5-points": "5",
      "6": "Container Runtime Security",
      "6-summary": "",
      "6-tier": "Advanced",
      "6-points": "6",
      "7": "Service Mesh Security",
      "7-summary": "",
      "7-tier": "Advanced",
      "7-points": "7",
      "8": "Identity-Based Perimeter",
      "8-summary": "",
      "8-tier": "Advanced",
      "8-points": "8"
        },
    "SecureData" : {
      "overview" : "Secure Data encompasses strategies and technologies aimed at protecting sensitive information from unauthorized access, modification, or disclosure. This involves employing encryption, access controls, and data masking techniques to safeguard data both in transit and at rest. By implementing robust security measures and adhering to compliance standards, organizations can mitigate the risks of data breaches and uphold the confidentiality, integrity, and availability of their data assets.",
      "qnum" : "2",
      "title" : "Secure Data",
      "1": "Classification",
      "1-summary": "",
      "1-tier": "Foundation",
      "1-points": "1",
      "2": "Encryption",
      "2-summary": "",
      "2-tier": "Foundation",
      "2-points": "2",
      "3": "Access Control",
      "3-summary": "",
      "3-tier": "Strategic",
      "3-points": "3",
      "4": "Tokenization",
      "4-summary": "",
      "4-tier": "Strategic",
      "4-points": "4",
      "5": "Loss Prevention",
      "5-summary": "",
      "5-tier": "Strategic",
      "5-points": "5",
      "6": "Automated Posture Management",
      "6-summary": "",
      "6-tier": "Advanced",
      "6-points": "6",
      "7": "Immutable Storage",
      "7-summary": "",
      "7-tier": "Advanced",
      "7-points": "7",
      "8": "Anomaly Detection",
      "8-summary": "",
      "8-tier": "Advanced",
      "8-points": "8"
      },
    "SecureIdentity" : {
      "overview" : "Secure Identity involves verifying and managing the digital identities of users accessing systems, networks, and applications to prevent unauthorized access and ensure trustworthiness. It encompasses techniques such as multi-factor authentication, biometrics, and identity federation to authenticate users securely and authorize access based on their roles and permissions. By implementing robust identity management practices, organizations can reduce the risk of identity theft, fraud, and unauthorized access to sensitive information.",
      "qnum" : "3",
      "title" : "Secure Identity",
      "1": "Passwords",
      "1-summary": "",
      "1-tier": "Foundation",
      "1-points": "1",
      "2": "Role-Based Access Control",
      "2-summary": "",
      "2-tier": "Foundation",
      "2-points": "2",
      "3": "Multi-Factor Identification",
      "3-summary": "",
      "3-tier": "Strategic",
      "3-points": "3",
      "4": "Single Sign On",
      "4-summary": "",
      "4-tier": "Strategic",
      "4-points": "4",
      "5": "Privileged Access Management",
      "5-summary": "",
      "5-tier": "Strategic",
      "5-points": "5",
      "6": "Identity Federation",
      "6-summary": "",
      "6-tier": "Advanced",
      "6-points": "6",
      "7": "AI/ML Anomaly Detection",
      "7-summary": "",
      "7-tier": "Advanced",
      "7-points": "7",
      "8": "Contextual / Risk Based Access",
      "8-summary": "",
      "8-tier": "Advanced",
      "8-points": "8"
    },
    "SecureApplication" : {
      "overview" : "Secure Applications refer to software programs and systems that are developed and maintained with a focus on mitigating security risks and vulnerabilities. This involves implementing secure coding practices, regular security assessments, and patch management to prevent exploitation by malicious actors. By prioritizing security throughout the software development lifecycle, organizations can ensure that their applications resist attacks and protect sensitive data from unauthorized access or manipulation.",
      "qnum" : "4",
      "title" : "Secure Application",
      "1": "Dependency Management",
      "1-summary": "",
      "1-tier": "Foundation",
      "1-points": "1",
      "2": "Static Application Security Testing",
      "2-summary": "",
      "2-tier": "Foundation",
      "2-points": "2",
      "3": "Secure Code Practices",
      "3-summary": "",
      "3-tier": "Strategic",
      "3-points": "3",
      "4": "Dynamic Application Security Testing",
      "4-summary": "",
      "4-tier": "Strategic",
      "4-points": "4",
      "5": "Web Application Firewall",
      "5-summary": "",
      "5-tier": "Strategic",
      "5-points": "5",
      "6": "Container Scanning",
      "6-summary": "",
      "6-tier": "Advanced",
      "6-points": "6",
      "7": "Runtime Application Self Protection",
      "7-summary": "",
      "7-tier": "Advanced",
      "7-points": "7",
      "8": "Interactive Application Security Testing",
      "8-summary": "",
      "8-tier": "Advanced",
      "8-points": "8"
    },  
    "SecureNetwork" : {
      "overview" : "Secure Network involves implementing measures to protect networks and data transmission from unauthorized access, interception, or tampering. This includes deploying firewalls, intrusion detection systems, and virtual private networks (VPNs) to safeguard communication channels and prevent external threats. By enforcing encryption protocols, segmenting networks, and regularly updating security configurations, organizations can maintain the integrity and confidentiality of their network infrastructure.",
      "qnum" : "5",
      "title" : "Secure Network",
      "1": "Firewalls & Segmentation",
      "1-summary": "",
      "1-tier": "Foundation",
      "1-points": "1",
      "2": "Secure Protocols",
      "2-summary": "",
      "2-tier": "Foundation",
      "2-points": "2",
      "3": "Access Control Lists",
      "3-summary": "",
      "3-tier": "Strategic",
      "3-points": "3",
      "4": "Intrusion Detection / Prevention",
      "4-summary": "",
      "4-tier": "Strategic",
      "4-points": "4",
      "5": "Traffic Analysis",
      "5-summary": "",
      "5-tier": "Strategic",
      "5-points": "5",
      "6": "Secure Connections",
      "6-summary": "",
      "6-tier": "Advanced",
      "6-points": "6",
      "7": "Microsegmentation",
      "7-summary": "",
      "7-tier": "Advanced",
      "7-points": "7",
      "8": "Zero Trust Network Access",
      "8-summary": "",
      "8-tier": "Advanced",
      "8-points": "8"
        },
    "SecureRecovery" : {
      "qnum" : "6",
      "overview" : "Secure Recovery refers to the process of restoring a system to a functional state after a disruption or compromise while ensuring the integrity and security of the recovered environment. It involves creating backups of critical data, implementing recovery procedures, and validating the authenticity of recovery components to prevent further damage or exploitation. By following secure recovery practices, organizations can minimize downtime, mitigate risks, and maintain trust in their systems' resilience against potential threats.",
      "title" : "Secure Recovery",
      "1": "Backup & Redundancy",
      "1-summary": "",
      "1-tier": "Foundation",
      "1-points": "1",
      "2": "Disaster Recovery Plan",
      "2-summary": "",
      "2-tier": "Foundation",
      "2-points": "2",
      "3": "Consistent Versioning",
      "3-summary": "",
      "3-tier": "Strategic",
      "3-points": "3",
      "4": "Automated Failovers",
      "4-summary": "",
      "4-tier": "Strategic",
      "4-points": "4",
      "5": "Lifecycle Management",
      "5-summary": "",
      "5-tier": "Strategic",
      "5-points": "5",
      "6": "Storage Scanning & Monitoring",
      "6-summary": "",
      "6-tier": "Advanced",
      "6-points": "6",
      "7": "Advanced Key Management",
      "7-summary": "",
      "7-tier": "Advanced",
      "7-points": "7",
      "8": "Predictive Recovery",
      "8-summary": "",
      "8-tier": "Advanced",
      "8-points": "8"
        },
    "SecureOperations" : {
      "overview" : "Secure Operations involves the implementation of policies, procedures, and technologies to ensure the ongoing security and integrity of an organization's systems and processes. This encompasses practices such as continuous monitoring, incident response planning, and security awareness training to detect and mitigate threats effectively. By integrating security into every aspect of operations, organizations can minimize risks, protect assets, and maintain the trust of stakeholders.",
      "qnum" : "7",
      "title" : "Secure Operations",
      "1": "Incident Response Plan",
      "1-summary": "",
      "1-tier": "Foundation",
      "1-points": "1",
      "2": "Anti-Virus scan",
      "2-summary": "",
      "2-tier": "Foundation",
      "2-points": "2",
      "3": "Security Information & Event Management",
      "3-summary": "",
      "3-tier": "Strategic",
      "3-points": "3",
      "4": "Endpoint Detection & Response",
      "4-summary": "",
      "4-tier": "Strategic",
      "4-points": "4",
      "5": "Orchestration, Automation, Response",
      "5-summary": "",
      "5-tier": "Strategic",
      "5-points": "5",
      "6": "Threat Intelligence Integration",
      "6-summary": "",
      "6-tier": "Advanced",
      "6-points": "6",
      "7": "APT Detection & Response",
      "7-summary": "",
      "7-tier": "Advanced",
      "7-points": "7",
      "8": "Purple Teaming",
      "8-summary": "",
      "8-tier": "Advanced",
      "8-points": "8"
        }
    } 